{
    "database": null,
    "default_limit": null,
    "desc": "获取可转债转股价变动",
    "id": 246,
    "if_exists": null,
    "inputs": [
        {
            "data_type": "str",
            "desc": "转债代码，支持多值输入",
            "must": "Y",
            "name": "ts_code"
        },
        {
            "data_type": "int",
            "desc": "单次返回数据长度",
            "must": "N",
            "name": "limit"
        },
        {
            "data_type": "int",
            "desc": "请求数据的开始位移量",
            "must": "N",
            "name": "offset"
        }
    ],
    "is_ready": null,
    "name": "cb_price_chg",
    "order_by": null,
    "outputs": [
        {
            "column": "TS_CODE",
            "data_type": "str",
            "desc": "转债代码",
            "must": "Y",
            "name": "ts_code"
        },
        {
            "column": "BOND_SHORT_NAME",
            "data_type": "str",
            "desc": "转债简称",
            "must": "Y",
            "name": "bond_short_name"
        },
        {
            "column": "PUBLISH_DATE",
            "data_type": "str",
            "desc": "公告日期",
            "must": "Y",
            "name": "publish_date"
        },
        {
            "column": "CHANGE_DATE",
            "data_type": "str",
            "desc": "变动日期",
            "must": "Y",
            "name": "change_date"
        },
        {
            "column": "CONVERT_PRICE_INITIAL",
            "data_type": "float",
            "desc": "初始转股价格",
            "must": "Y",
            "name": "convert_price_initial"
        },
        {
            "column": "CONVERTPRICE_BEF",
            "data_type": "float",
            "desc": "修正前转股价格",
            "must": "Y",
            "name": "convertprice_bef"
        },
        {
            "column": "CONVERTPRICE_AFT",
            "data_type": "float",
            "desc": "修正后转股价格",
            "must": "Y",
            "name": "convertprice_aft"
        }
    ],
    "parent_id": 184,
    "path": [
        [
            2,
            "数据接口"
        ],
        [
            184,
            "债券"
        ],
        [
            246,
            "可转债转股价变动"
        ]
    ],
    "title": "可转债转股价变动",
    "validations": []
}