{
  "database": null,
  "default_limit": "2000",
  "desc": "获取美国国债长期利率平均值数据",
  "id": 223,
  "integral_required": 120,
  "if_exists": null,
  "inputs": [
    {
      "data_type": "str",
      "desc": "日期",
      "must": "N",
      "name": "date"
    },
    {
      "data_type": "str",
      "desc": "开始日期",
      "must": "N",
      "name": "start_date"
    },
    {
      "data_type": "str",
      "desc": "结束日期",
      "must": "N",
      "name": "end_date"
    },
    {
      "data_type": "str",
      "desc": "指定字段",
      "must": "N",
      "name": "fields"
    },
    {
      "data_type": "int",
      "desc": "单次返回数据长度",
      "must": "N",
      "name": "limit"
    },
    {
      "data_type": "int",
      "desc": "请求数据的开始位移量",
      "must": "N",
      "name": "offset"
    }
  ],
  "is_ready": null,
  "name": "us_trltr",
  "order_by": null,
  "outputs": [
    {
      "column": "DATE",
      "data_type": "str",
      "desc": "日期",
      "must": "Y",
      "name": "date"
    },
    {
      "column": "LTR_AVG",
      "data_type": "float",
      "desc": "实际平均利率LT Real Average (10> Yrs)",
      "must": "Y",
      "name": "ltr_avg"
    }
  ],
  "parent_id": 218,
  "path": [
    [
      2,
      "数据接口"
    ],
    [
      147,
      "宏观经济"
    ],
    [
      217,
      "国际宏观"
    ],
    [
      218,
      "美国利率"
    ],
    [
      223,
      "国债长期利率平均值"
    ]
  ],
  "title": "国债长期利率平均值",
  "validations": []
}