{
    "desc": "市场每日交易统计",
    "name": "daily_info",
    "id": 215,
    "outputs": [{
        "column": "TRADE_DATE",
        "name": "trade_date",
        "data_type": "str",
        "must": "Y",
        "desc": "交易日期"
    }, {
        "column": "TS_CODE",
        "name": "ts_code",
        "data_type": "str",
        "must": "Y",
        "desc": "市场代码"
    }, {
        "column": "TS_NAME",
        "name": "ts_name",
        "data_type": "str",
        "must": "Y",
        "desc": "市场名称"
    }, {
        "column": "COM_COUNT",
        "name": "com_count",
        "data_type": "int",
        "must": "Y",
        "desc": "挂牌数"
    }, {
        "column": "TOTAL_SHARE",
        "name": "total_share",
        "data_type": "float",
        "must": "Y",
        "desc": "总股本（亿股）"
    }, {
        "column": "FLOAT_SHARE",
        "name": "float_share",
        "data_type": "float",
        "must": "Y",
        "desc": "流通股本（亿股）"
    }, {
        "column": "TOTAL_MV",
        "name": "total_mv",
        "data_type": "float",
        "must": "Y",
        "desc": "总市值（亿元）"
    }, {
        "column": "FLOAT_MV",
        "name": "float_mv",
        "data_type": "float",
        "must": "Y",
        "desc": "流通市值（亿元）"
    }, {
        "column": "AMOUNT",
        "name": "amount",
        "data_type": "float",
        "must": "Y",
        "desc": "交易金额（亿元）"
    }, {
        "column": "VOL",
        "name": "vol",
        "data_type": "float",
        "must": "Y",
        "desc": "成交量（亿股）"
    }, {
        "column": "TRANS_COUNT",
        "name": "trans_count",
        "data_type": "int",
        "must": "Y",
        "desc": "成交笔数（万笔）"
    }, {
        "column": "PE",
        "name": "pe",
        "data_type": "float",
        "must": "Y",
        "desc": "平均市盈率"
    }, {
        "column": "TR",
        "name": "tr",
        "data_type": "float",
        "must": "Y",
        "desc": "换手率（％）"
    }, {
        "column": "EXCHANGE",
        "name": "exchange",
        "data_type": "str",
        "must": "Y",
        "desc": "交易所"
    }],
    "database": null,
    "is_ready": null,
    "if_exists": null,
    "parent_id": 93,
    "title": "沪深市场每日交易统计",
    "inputs": [{
        "name": "trade_date",
        "data_type": "str",
        "must": "N",
        "desc": "交易日期"
    }, {
        "name": "ts_code",
        "data_type": "str",
        "must": "N",
        "desc": "板块代码"
    }, {
        "name": "exchange",
        "data_type": "str",
        "must": "N",
        "desc": "股票市场"
    }, {
        "name": "start_date",
        "data_type": "str",
        "must": "N",
        "desc": "开始日期"
    }, {
        "name": "end_date",
        "data_type": "str",
        "must": "N",
        "desc": "结束日期"
    }, {
        "name": "limit",
        "data_type": "int",
        "must": "N",
        "desc": "单次返回数据长度"
    }, {
        "name": "offset",
        "data_type": "int",
        "must": "N",
        "desc": "请求数据的开始位移量"
    }],
    "validations": [],
    "default_limit": null,
    "order_by": null
}
